mp4_to_jpg/__init__.py
mp4_to_jpg/mp4_to_jpg.py
mp4_to_jpg-1.0.6.dist-info/METADATA
mp4_to_jpg-1.0.6.dist-info/WHEEL
mp4_to_jpg-1.0.6.dist-info/entry_points.txt
mp4_to_jpg-1.0.6.dist-info/top_level.txt
mp4_to_jpg-1.0.6.dist-info/RECORD
