Metadata-Version: 2.1
Name: mp4_to_jpg
Version: 1.0.6
Summary: A tool to extract frames from MP4 videos and remove duplicates
Home-page: https://github.com/tadeasf/mp4-to-jpg_click
Author: Tadeas Fort
Author-email: taddy.fort@gmail.com
Classifier: Programming Language :: Python :: 3
Classifier: License :: OSI Approved :: MIT License
Classifier: Operating System :: OS Independent
Requires-Python: >=3.11
Requires-Dist: rich-click
Requires-Dist: opencv-python
Requires-Dist: tk
Requires-Dist: tqdm
Requires-Dist: loguru
Requires-Dist: imagededup
